deriva/__init__.py
deriva/chisel/__init__.py
deriva/chisel/catalog/__init__.py
deriva/chisel/catalog/ext.py
deriva/chisel/catalog/model.py
deriva/chisel/catalog/semistructured.py
deriva/chisel/catalog/stubs.py
deriva/chisel/catalog/wrapper.py
deriva/chisel/mmo/__init__.py
deriva/chisel/operators/__init__.py
deriva/chisel/operators/base.py
deriva/chisel/operators/ermrest.py
deriva/chisel/operators/graph.py
deriva/chisel/operators/semistructured.py
deriva/chisel/optimizer/__init__.py
deriva/chisel/optimizer/consolidate.py
deriva/chisel/optimizer/rules.py
deriva/chisel/optimizer/symbols.py
deriva/chisel/util/__init__.py
deriva/chisel/util/describe.py
deriva/chisel/util/graph.py
test/__init__.py
test/helpers.py
test/catalog/__init__.py
test/catalog/test_base.py
test/catalog/test_computedrelation.py
test/catalog/test_ermrest.py
test/catalog/test_semistruct_csv.py
test/catalog/test_semistruct_json.py
test/mmo/__init__.py
test/mmo/base.py
test/mmo/test_mmo_drop.py
test/mmo/test_mmo_find.py
test/mmo/test_mmo_prune.py
test/mmo/test_mmo_rename.py
test/mmo/test_mmo_replace.py
test/mmo/test_mmo_smo.py
test/operators/__init__.py
test/operators/test_crossjoin.py
test/operators/test_jsonscan.py
test/operators/test_project.py
test/operators/test_rename.py
test/operators/test_select.py
test/operators/test_shred.py
test/operators/test_similarityaggr.py
test/operators/test_similarityjoin.py
test/optimizer/__init__.py
test/optimizer/test_consolidate.py
test/optimizer/test_domainify.py
test/optimizer/test_jsonscan.py
test/util/__init__.py
test/util/test_edit_distance.py
deriva_chisel-0.3.1.dist-info/LICENSE
deriva_chisel-0.3.1.dist-info/METADATA
deriva_chisel-0.3.1.dist-info/WHEEL
deriva_chisel-0.3.1.dist-info/top_level.txt
deriva_chisel-0.3.1.dist-info/RECORD
