Metadata-Version: 2.1
Name: deriva-chisel
Version: 0.3.1
Summary: CHiSEL: schema evolution and model management for the DERIVA platform.
Home-page: https://github.com/informatics-isi-edu/chisel/
Author: USC Information Sciences Institute, Informatics Systems Research Division
Author-email: isrd-support@isi.edu
Maintainer: USC Information Sciences Institute, Informatics Systems Research Division
Maintainer-email: isrd-support@isi.edu
License: Apache 2.0
Classifier: Intended Audience :: Science/Research
Classifier: Intended Audience :: Developers
Classifier: License :: OSI Approved :: Apache Software License
Classifier: Operating System :: POSIX
Classifier: Operating System :: MacOS :: MacOS X
Classifier: Operating System :: Microsoft :: Windows
Classifier: Programming Language :: Python
Classifier: Programming Language :: Python :: 3.7
Classifier: Programming Language :: Python :: 3.8
Classifier: Programming Language :: Python :: 3.9
License-File: LICENSE
Requires-Dist: deriva <=1.7.3,>=1.5.0
Requires-Dist: graphviz
Requires-Dist: nltk
Requires-Dist: pyfpm
Requires-Dist: pyparsing
Requires-Dist: rdflib
